sqlalchemy_mate/__init__.py
sqlalchemy_mate/_version.py
sqlalchemy_mate/api.py
sqlalchemy_mate/engine_creator.py
sqlalchemy_mate/io.py
sqlalchemy_mate/io_api.py
sqlalchemy_mate/paths.py
sqlalchemy_mate/pt.py
sqlalchemy_mate/pt_api.py
sqlalchemy_mate/utils.py
sqlalchemy_mate/crud/__init__.py
sqlalchemy_mate/crud/deleting.py
sqlalchemy_mate/crud/deleting_api.py
sqlalchemy_mate/crud/inserting.py
sqlalchemy_mate/crud/inserting_api.py
sqlalchemy_mate/crud/selecting.py
sqlalchemy_mate/crud/selecting_api.py
sqlalchemy_mate/crud/updating.py
sqlalchemy_mate/crud/updating_api.py
sqlalchemy_mate/docs/__init__.py
sqlalchemy_mate/orm/__init__.py
sqlalchemy_mate/orm/api.py
sqlalchemy_mate/orm/extended_declarative_base.py
sqlalchemy_mate/patterns/__init__.py
sqlalchemy_mate/patterns/api.py
sqlalchemy_mate/patterns/large_binary_column/__init__.py
sqlalchemy_mate/patterns/large_binary_column/api.py
sqlalchemy_mate/patterns/large_binary_column/aws_s3.py
sqlalchemy_mate/patterns/large_binary_column/aws_s3_api.py
sqlalchemy_mate/patterns/large_binary_column/helpers.py
sqlalchemy_mate/patterns/large_binary_column/local.py
sqlalchemy_mate/patterns/large_binary_column/local_api.py
sqlalchemy_mate/patterns/status_tracker/__init__.py
sqlalchemy_mate/patterns/status_tracker/api.py
sqlalchemy_mate/patterns/status_tracker/impl.py
sqlalchemy_mate/tests/__init__.py
sqlalchemy_mate/tests/api.py
sqlalchemy_mate/tests/constants.py
sqlalchemy_mate/tests/crud_test.py
sqlalchemy_mate/tests/engine.py
sqlalchemy_mate/tests/helper.py
sqlalchemy_mate/tests/mock_aws.py
sqlalchemy_mate/tests/status_tracker_test.py
sqlalchemy_mate/types/__init__.py
sqlalchemy_mate/types/api.py
sqlalchemy_mate/types/compressed.py
sqlalchemy_mate/types/compressed_json.py
sqlalchemy_mate/types/json_serializable.py
sqlalchemy_mate/vendor/__init__.py
sqlalchemy_mate/vendor/iterable.py
sqlalchemy_mate/vendor/pytest_cov_helper.py
sqlalchemy_mate/vendor/timeout_decorator/__init__.py
sqlalchemy_mate-2.0.0.3.dist-info/AUTHORS.rst
sqlalchemy_mate-2.0.0.3.dist-info/LICENSE.txt
sqlalchemy_mate-2.0.0.3.dist-info/METADATA
sqlalchemy_mate-2.0.0.3.dist-info/WHEEL
sqlalchemy_mate-2.0.0.3.dist-info/top_level.txt
sqlalchemy_mate-2.0.0.3.dist-info/RECORD
