Metadata-Version: 2.1
Name: sqlalchemy_mate
Version: 2.0.0.3
Summary: A library extend sqlalchemy module, makes CRUD easier.
Home-page: https://github.com/MacHu-GWU/sqlalchemy_mate-project
Download-URL: https://pypi.python.org/pypi/sqlalchemy_mate/2.0.0.3#downloads
Author: Sanhe Hu
Author-email: husanhe@gmail.com
Maintainer: Unknown
License: MIT
Platform: Windows
Platform: MacOS
Platform: Unix
Classifier: Development Status :: 4 - Beta
Classifier: Intended Audience :: Developers
Classifier: License :: OSI Approved :: MIT License
Classifier: Natural Language :: English
Classifier: Operating System :: Microsoft :: Windows
Classifier: Operating System :: MacOS
Classifier: Operating System :: Unix
Classifier: Programming Language :: Python
Classifier: Programming Language :: Python :: 3.8
Classifier: Programming Language :: Python :: 3.9
Classifier: Programming Language :: Python :: 3.10
Classifier: Programming Language :: Python :: 3.11
Classifier: Programming Language :: Python :: 3.12
Classifier: Programming Language :: Python :: 3 :: Only
Requires-Python: >=3.8
License-File: LICENSE.txt
License-File: AUTHORS.rst
Requires-Dist: sqlalchemy<3.0.0,>=2.0.0
Requires-Dist: prettytable<4.0.0,>=3.0.0
Provides-Extra: tests
Requires-Dist: pytest; extra == "tests"
Requires-Dist: pytest-cov; extra == "tests"
Requires-Dist: pg8000; extra == "tests"
Requires-Dist: attrs; extra == "tests"
Requires-Dist: superjson; extra == "tests"
Requires-Dist: pandas<3.0.0,>=2.0.0; extra == "tests"
Requires-Dist: moto<5.0.0,>=4.1.12; extra == "tests"
Requires-Dist: boto_session_manager<2.0.0,>=1.7.2; extra == "tests"
Requires-Dist: s3pathlib<3.0.0,>=2.1.2; extra == "tests"
Provides-Extra: docs
Requires-Dist: Sphinx==5.3.0; extra == "docs"
Requires-Dist: sphinx-jinja==2.0.2; extra == "docs"
Requires-Dist: sphinx-copybutton==0.5.1; extra == "docs"
Requires-Dist: sphinx-design==0.5.0; extra == "docs"
Requires-Dist: furo==2023.03.27; extra == "docs"
Requires-Dist: nbsphinx==0.8.12; extra == "docs"
Requires-Dist: rstobj==1.2.1; extra == "docs"
Requires-Dist: pygments==2.15.1; extra == "docs"
Requires-Dist: ipython==8.10.0; extra == "docs"
Requires-Dist: docfly==2.0.3; extra == "docs"
